specification_curve/__init__.py
specification_curve/__main__.py
specification_curve/data/example_data.csv
specification_curve-0.3.9.dist-info/METADATA
specification_curve-0.3.9.dist-info/WHEEL
specification_curve-0.3.9.dist-info/top_level.txt
specification_curve-0.3.9.dist-info/RECORD
