Metadata-Version: 2.4
Name: specification_curve
Version: 0.3.9
Summary: Specification_Curve
License-Expression: MIT
Classifier: Development Status :: 4 - Beta
Classifier: Programming Language :: Python :: 3.10
Classifier: Programming Language :: Python :: 3.11
Classifier: Programming Language :: Python :: 3.12
Classifier: Programming Language :: Python :: 3.13
Requires-Python: >=3.10
Requires-Dist: matplotlib>=3.9.4
Requires-Dist: numpy>=2.0.2
Requires-Dist: pandas-stubs>=2.2.2.240807
Requires-Dist: pandas>=2.2.3
Requires-Dist: statsmodels>=0.14.4
Requires-Dist: typeguard>=4.4.1
Requires-Dist: types-setuptools>=75.6.0.20241223
Requires-Dist: nbclient>=0.10.2
Requires-Dist: tqdm>=4.67.1
Requires-Dist: pingouin>=0.5.5
Requires-Dist: types-tqdm>=4.67.0.20241221
Requires-Dist: ipywidgets>=8.1.5
